Metadata-Version: 2.4
Name: mabel
Version: 0.6.29
Summary: Python Data Libraries
Home-page: https://github.com/mabel-dev/mabel/
Author: joocer
Author-email: justin.joyce@joocer.com
Maintainer: Joocer
License-File: LICENSE
License-File: NOTICE
Requires-Dist: bitarray
Requires-Dist: lz4
Requires-Dist: orjson
Requires-Dist: orso>=0.0.147
Requires-Dist: xxhash
Requires-Dist: zstandard
Dynamic: author
Dynamic: author-email
Dynamic: description
Dynamic: description-content-type
Dynamic: home-page
Dynamic: license-file
Dynamic: maintainer
Dynamic: requires-dist
Dynamic: summary
